anyserver.py
fabfile.py
setup.py
setupbase.py
web2py.py
applications/admin/__init__.py
applications/admin/controllers/appadmin.py
applications/admin/controllers/debug.py
applications/admin/controllers/default.py
applications/admin/controllers/gae.py
applications/admin/controllers/mercurial.py
applications/admin/controllers/openshift.py
applications/admin/controllers/plugin_jqmobile.py
applications/admin/controllers/pythonanywhere.py
applications/admin/controllers/toolbar.py
applications/admin/controllers/webservices.py
applications/admin/controllers/wizard.py
applications/admin/cron/expire_sessions.py
applications/admin/languages/af.py
applications/admin/languages/bg.py
applications/admin/languages/cs.py
applications/admin/languages/de.py
applications/admin/languages/en.py
applications/admin/languages/es.py
applications/admin/languages/fr.py
applications/admin/languages/he.py
applications/admin/languages/it.py
applications/admin/languages/ja.py
applications/admin/languages/my-mm.py
applications/admin/languages/nl.py
applications/admin/languages/pl.py
applications/admin/languages/plural-en.py
applications/admin/languages/plural-ru.py
applications/admin/languages/plural-uk.py
applications/admin/languages/pt-br.py
applications/admin/languages/pt.py
applications/admin/languages/ro.py
applications/admin/languages/ru.py
applications/admin/languages/sl.py
applications/admin/languages/sr-cr.py
applications/admin/languages/sr-lt.py
applications/admin/languages/tr.py
applications/admin/languages/uk.py
applications/admin/languages/zh-tw.py
applications/admin/languages/zh.py
applications/admin/models/0.py
applications/admin/models/0_imports.py
applications/admin/models/access.py
applications/admin/models/buttons.py
applications/admin/models/db.py
applications/admin/models/menu.py
applications/admin/models/plugin_multiselect.py
applications/admin/models/plugin_statebutton.py
applications/admin/modules/__init__.py
applications/examples/__init__.py
web2py_gluon-2.26.1.dist-info/METADATA
web2py_gluon-2.26.1.dist-info/WHEEL
web2py_gluon-2.26.1.dist-info/licenses/LICENSE
web2py_gluon-2.26.1.dist-info/RECORD
